plone.app.event-5.2.3-py3.13-nspkg.pth
plone/app/event/__init__.py
plone/app/event/adapters.py
plone/app/event/base.py
plone/app/event/configure.zcml
plone/app/event/interfaces.py
plone/app/event/permissions.zcml
plone/app/event/recurrence.py
plone/app/event/recurrence.zcml
plone/app/event/setuphandlers.py
plone/app/event/testing.py
plone/app/event/vocabularies.py
plone/app/event/browser/__init__.py
plone/app/event/browser/configure.zcml
plone/app/event/browser/event_listing.pt
plone/app/event/browser/event_listing.py
plone/app/event/browser/event_summary.pt
plone/app/event/browser/event_summary.py
plone/app/event/browser/event_view.pt
plone/app/event/browser/event_view.py
plone/app/event/browser/formatted_date.pt
plone/app/event/browser/formatted_date.py
plone/app/event/browser/formatted_start_date.pt
plone/app/event/browser/leadimage_viewlet.py
plone/app/event/browser/resources/calendar.svg
plone/app/event/browser/resources/event.js
plone/app/event/dx/__init__.py
plone/app/event/dx/behaviors.py
plone/app/event/dx/configure.zcml
plone/app/event/dx/ical.zcml
plone/app/event/dx/interfaces.py
plone/app/event/dx/traverser.py
plone/app/event/ical/__init__.py
plone/app/event/ical/configure.zcml
plone/app/event/ical/exporter.py
plone/app/event/ical/importer.py
plone/app/event/portlets/__init__.py
plone/app/event/portlets/configure.zcml
plone/app/event/portlets/portlet_calendar.pt
plone/app/event/portlets/portlet_calendar.py
plone/app/event/portlets/portlet_events.pt
plone/app/event/portlets/portlet_events.py
plone/app/event/profiles/default/actions.xml
plone/app/event/profiles/default/browserlayer.xml
plone/app/event/profiles/default/controlpanel.xml
plone/app/event/profiles/default/metadata.xml
plone/app/event/profiles/default/plone.app.event-default.txt
plone/app/event/profiles/default/portlets.xml
plone/app/event/profiles/default/registry.xml
plone/app/event/profiles/default/rolemap.xml
plone/app/event/profiles/default/types.xml
plone_app_event-5.2.3.dist-info/licenses/LICENSE.GPL
plone_app_event-5.2.3.dist-info/licenses/LICENSE.rst
plone_app_event-5.2.3.dist-info/METADATA
plone_app_event-5.2.3.dist-info/WHEEL
plone_app_event-5.2.3.dist-info/namespace_packages.txt
plone_app_event-5.2.3.dist-info/top_level.txt
plone_app_event-5.2.3.dist-info/RECORD
