Metadata-Version: 2.4
Name: plone.app.event
Version: 5.2.3
Summary: The Plone calendar framework
Home-page: https://github.com/plone/plone.app.event
Author: Plone Foundation
Author-email: plone-developers@lists.sourceforge.net
License: GPL version 2
Keywords: plone event
Classifier: Development Status :: 5 - Production/Stable
Classifier: Framework :: Plone
Classifier: Framework :: Plone :: 6.0
Classifier: Framework :: Plone :: Core
Classifier: License :: OSI Approved :: GNU General Public License v2 (GPLv2)
Classifier: Programming Language :: Python
Classifier: Programming Language :: Python :: 3.8
Classifier: Programming Language :: Python :: 3.9
Classifier: Programming Language :: Python :: 3.10
Classifier: Programming Language :: Python :: 3.11
Requires-Python: >=3.8
License-File: LICENSE.GPL
License-File: LICENSE.rst
Requires-Dist: setuptools
Requires-Dist: plone.base
Requires-Dist: Products.statusmessages
Requires-Dist: icalendar
Requires-Dist: Products.DateRecurringIndex
Requires-Dist: Products.ZCatalog
Requires-Dist: Products.GenericSetup
Requires-Dist: plone.app.contentmenu
Requires-Dist: plone.app.contenttypes
Requires-Dist: plone.app.uuid
Requires-Dist: plone.resource
Requires-Dist: plone.app.contentlisting
Requires-Dist: plone.app.dexterity
Requires-Dist: plone.app.portlets>=2.5.1
Requires-Dist: plone.app.querystring
Requires-Dist: plone.app.registry
Requires-Dist: plone.app.textfield
Requires-Dist: plone.app.vocabularies>=2.1.15
Requires-Dist: plone.app.z3cform>=2.0.1
Requires-Dist: plone.autoform>=1.4
Requires-Dist: plone.behavior
Requires-Dist: plone.browserlayer
Requires-Dist: plone.dexterity
Requires-Dist: plone.event>=1.0
Requires-Dist: plone.folder
Requires-Dist: plone.formwidget.recurrence[z3cform]>=1.2.4
Requires-Dist: plone.indexer
Requires-Dist: plone.memoize
Requires-Dist: plone.namedfile
Requires-Dist: plone.portlets
Requires-Dist: plone.supermodel
Requires-Dist: plone.uuid
Requires-Dist: pytz
Requires-Dist: z3c.form>=3.2.1
Requires-Dist: Zope
Provides-Extra: test
Requires-Dist: plone.app.robotframework; extra == "test"
Requires-Dist: plone.app.testing[robot]; extra == "test"
Requires-Dist: plone.testing; extra == "test"
Requires-Dist: robotsuite; extra == "test"
Requires-Dist: lxml; extra == "test"
Dynamic: author
Dynamic: author-email
Dynamic: classifier
Dynamic: description
Dynamic: description-content-type
Dynamic: home-page
Dynamic: keywords
Dynamic: license
Dynamic: license-file
Dynamic: provides-extra
Dynamic: requires-dist
Dynamic: requires-python
Dynamic: summary
